color_picker/__init__.py
color_picker/color_picker.py
color_picker/assets/cast-grayscale.png
color_picker/assets/cast.png
color_picker/assets/deuman.png
color_picker/assets/human-newman.png
color_picker/assets/reticle.png
color_picker/assets/slider.png
color_picker/assets/window_ui.png
pso2_color_picker-0.1.3.dist-info/LICENSE
pso2_color_picker-0.1.3.dist-info/METADATA
pso2_color_picker-0.1.3.dist-info/WHEEL
pso2_color_picker-0.1.3.dist-info/entry_points.txt
pso2_color_picker-0.1.3.dist-info/top_level.txt
pso2_color_picker-0.1.3.dist-info/RECORD
