Metadata-Version: 2.1
Name: pso2-color-picker
Version: 0.1.3
Summary: A color matching tool for PSO2.
Home-page: https://github.com/jrg94/color-picker
Author: The Renegade Coder
Author-email: jeremy.grifski@therenegadecoder.com
License: UNKNOWN
Platform: UNKNOWN
Classifier: Programming Language :: Python :: 3.8
Classifier: Operating System :: OS Independent
Requires-Python: >=3.8
Requires-Dist: pillow (>=6.0.0)
Requires-Dist: numpy (==1.19.3)
